si_seqfs_da/BackwardSelection.py
si_seqfs_da/DA_SeqFS.py
si_seqfs_da/ForwardSelection.py
si_seqfs_da/OptimalTransport.py
si_seqfs_da/SI_SeqFS_DA.py
si_seqfs_da/__init__.py
si_seqfs_da/gendata.py
si_seqfs_da/intersection.py
si_seqfs_da/overconditioning.py
si_seqfs_da/overconditioningBS.py
si_seqfs_da/parametric.py
si_seqfs_da-1.1.dist-info/LICENSE
si_seqfs_da-1.1.dist-info/METADATA
si_seqfs_da-1.1.dist-info/WHEEL
si_seqfs_da-1.1.dist-info/top_level.txt
si_seqfs_da-1.1.dist-info/RECORD
