Metadata-Version: 2.2
Name: si_seqfs_da
Version: 1.1
Summary: Statistical Inference for Sequential Feature Selection after Domain Adaptation
Home-page: https://github.com/locluclak/SI-SeqFS-DA
Author: Duong Tan Loc
Author-email: 235202854@gm.uit.edu.vn
Classifier: Programming Language :: Python :: 3
Classifier: License :: OSI Approved :: MIT License
Classifier: Operating System :: OS Independent
License-File: LICENSE
Dynamic: author
Dynamic: author-email
Dynamic: classifier
Dynamic: description
Dynamic: description-content-type
Dynamic: home-page
Dynamic: summary
